Escher-1.8.1.data/data/etc/jupyter/nbconfig/notebook.d/escher.json
Escher-1.8.1.data/data/share/jupyter/nbextensions/escher/escher.min.js
Escher-1.8.1.data/data/share/jupyter/nbextensions/escher/escher.min.js.map
Escher-1.8.1.data/data/share/jupyter/nbextensions/escher/extension.js
escher/__init__.py
escher/plots.py
escher/urls.py
escher/util.py
escher/validate.py
escher/version.py
escher/static/escher.min.js
escher/static/escher.min.js.map
escher/static/extension.js
escher/static/package.json
escher/static/jsonschema/1-0-0
escher/templates/standalone.html
Escher-1.8.1.dist-info/METADATA
Escher-1.8.1.dist-info/WHEEL
Escher-1.8.1.dist-info/top_level.txt
Escher-1.8.1.dist-info/RECORD
