Metadata-Version: 2.1
Name: Escher
Version: 1.8.1
Summary: Escher: A Web Application for Building, Sharing, and Embedding Data-Rich Visualizations of Metabolic Pathways
Home-page: https://escher.github.io
Author: Zachary King
License: MIT
Keywords: visualization,pathway map,metabolism,genome-scale-model,web application,D3.js,biojs
Classifier: Development Status :: 5 - Production/Stable
Classifier: License :: OSI Approved :: MIT License
Classifier: Topic :: Scientific/Engineering
Classifier: Topic :: Scientific/Engineering :: Visualization
Classifier: Programming Language :: Python :: 3
Classifier: Programming Language :: Python :: 3.10
Classifier: Programming Language :: Python :: 3.11
Classifier: Programming Language :: Python :: 3.12
Classifier: Operating System :: OS Independent
Requires-Dist: Jinja2<4,>=3.0.3
Requires-Dist: pytest<9,>=6.0.0
Requires-Dist: cobra>=0.5.0
Requires-Dist: jsonschema<5,>=4.17.3
Requires-Dist: ipywidgets<8,>=7.7.0
Requires-Dist: pandas>=0.18
Provides-Extra: docs
Requires-Dist: sphinx<9,>=8.1.3; extra == "docs"
Requires-Dist: sphinx-rtd-theme<4,>=3.0.1; extra == "docs"
Requires-Dist: nbsphinx<1,>=0.9.5; extra == "docs"
Provides-Extra: jupyter
Requires-Dist: jupyterlab-widgets==1.1.1; extra == "jupyter"
Requires-Dist: jupyterlab==3.6.3; extra == "jupyter"
Provides-Extra: test
Requires-Dist: pytest<9,>=6.0.0; extra == "test"
